AndroidKeepAwake/__init__.py
AndroidKeepAwake-1.1.dist-info/LICENSE
AndroidKeepAwake-1.1.dist-info/METADATA
AndroidKeepAwake-1.1.dist-info/WHEEL
AndroidKeepAwake-1.1.dist-info/top_level.txt
AndroidKeepAwake-1.1.dist-info/RECORD
