Metadata-Version: 2.1
Name: AndroidKeepAwake
Version: 1.1
Summary: Keep you Android device awake when your application is running.
Home-page: https://github.com/ziyaad30/AndroidKeepAwake
Author: ziyaad30
Author-email: xavier.baatjes@outlook.com
License: UNKNOWN
Project-URL: Bug Tracker, https://github.com/ziyaad30/AndroidKeepAwake/issues
Platform: UNKNOWN
Classifier: Programming Language :: Python :: 3
Classifier: License :: OSI Approved :: MIT License
Classifier: Operating System :: OS Independent
Requires-Python: >=3.8
License-File: LICENSE
